xlsx2md/__init__.py
xlsx2md/__main__.py
xlsx2md/cli.py
xlsx2md/config.py
xlsx2md/renderer.py
xlsx2md/utils.py
xlsx2md/validator.py
xlsx2md/readers/__init__.py
xlsx2md/readers/base.py
xlsx2md/readers/csv_reader.py
xlsx2md/readers/xls_reader.py
xlsx2md/readers/xlsx_reader.py
xlsx2md-0.1.1.dist-info/METADATA
xlsx2md-0.1.1.dist-info/WHEEL
xlsx2md-0.1.1.dist-info/entry_points.txt
xlsx2md-0.1.1.dist-info/top_level.txt
xlsx2md-0.1.1.dist-info/RECORD
