Metadata-Version: 2.4
Name: xlsx2md
Version: 0.1.1
Summary: Convert Excel files (xlsx, xls) and CSV to Markdown tables
Author-email: Roman Postovalov <rpostovalov@gmail.com>
License: MIT
Project-URL: Homepage, https://github.com/postovalov/xlsx2md
Project-URL: Repository, https://github.com/postovalov/xlsx2md
Project-URL: Issues, https://github.com/postovalov/xlsx2md/issues
Keywords: excel,xlsx,xls,csv,markdown,table,converter
Classifier: Development Status :: 3 - Alpha
Classifier: Intended Audience :: Developers
Classifier: License :: OSI Approved :: MIT License
Classifier: Programming Language :: Python :: 3
Classifier: Programming Language :: Python :: 3.8
Classifier: Programming Language :: Python :: 3.9
Classifier: Programming Language :: Python :: 3.10
Classifier: Programming Language :: Python :: 3.11
Classifier: Programming Language :: Python :: 3.12
Classifier: Topic :: Text Processing :: Markup
Classifier: Topic :: Utilities
Requires-Python: >=3.8
Requires-Dist: openpyxl>=3.0.0
Requires-Dist: xlrd>=2.0.0
Requires-Dist: typer>=0.9.0
Requires-Dist: rich>=13.0.0
Requires-Dist: chardet>=5.0.0
Provides-Extra: dev
Requires-Dist: pytest>=7.0.0; extra == "dev"
Requires-Dist: pytest-cov>=4.0.0; extra == "dev"
Requires-Dist: black>=23.0.0; extra == "dev"
Requires-Dist: flake8>=6.0.0; extra == "dev"
Requires-Dist: mypy>=1.0.0; extra == "dev"
